hanaro/ConfigFilter.py
hanaro/ContextInjectionFilter.py
hanaro/QueuedHandler.py
hanaro/__init__.py
hanaro/utils.py
hanaro-0.1.7.dist-info/licenses/LICENSE
hanaro-0.1.7.dist-info/METADATA
hanaro-0.1.7.dist-info/WHEEL
hanaro-0.1.7.dist-info/top_level.txt
hanaro-0.1.7.dist-info/RECORD
