Metadata-Version: 2.4
Name: hanaro
Version: 0.1.7
Summary: A non-invasive `logging` configurator and facilitator.
Author-email: Shaun Wilson <mrshaunwilson@msn.com>
License-Expression: MIT
Project-URL: Documentation, https://hanaro.readthedocs.io/
Project-URL: Homepage, https://github.com/wilson0x4d/hanaro
Project-URL: Repository, https://github.com/wilson0x4d/hanaro.git
Keywords: logging,configuration,appsettings2,async
Classifier: Operating System :: OS Independent
Classifier: Programming Language :: Python :: 3.12
Classifier: Programming Language :: Python :: 3.13
Classifier: Topic :: Software Development :: Libraries :: Python Modules
Classifier: Intended Audience :: Developers
Requires-Python: >=3.12
License-File: LICENSE
Requires-Dist: appsettings2>=1.2.6
Provides-Extra: dev
Requires-Dist: build; extra == "dev"
Requires-Dist: punit>=1.1.4; extra == "dev"
Requires-Dist: twine; extra == "dev"
Dynamic: license-file
